dict_from_annotation/__init__.py
dict_from_annotation/annotation_handling.py
dict_from_annotation/argparse_helper.py
dict_from_annotation/cli.py
dict_from_annotation/main.py
dict_from_annotation-0.0.2.dist-info/LICENSE
dict_from_annotation-0.0.2.dist-info/METADATA
dict_from_annotation-0.0.2.dist-info/WHEEL
dict_from_annotation-0.0.2.dist-info/entry_points.txt
dict_from_annotation-0.0.2.dist-info/top_level.txt
dict_from_annotation-0.0.2.dist-info/RECORD
